spawnbox/__init__.py
spawnbox/entity.py
spawnbox/input.py
spawnbox/main.py
spawnbox/sprites.py
spawnbox/ext/__init__.py
spawnbox/ext/animation.py
spawnbox/ext/audio.py
spawnbox/ext/text.py
spawnbox-0.1.0.dist-info/licenses/LICENSE
spawnbox-0.1.0.dist-info/METADATA
spawnbox-0.1.0.dist-info/WHEEL
spawnbox-0.1.0.dist-info/top_level.txt
spawnbox-0.1.0.dist-info/RECORD
